FashTextPy/__init__.py
FashTextPy-1.1.dist-info/METADATA
FashTextPy-1.1.dist-info/WHEEL
FashTextPy-1.1.dist-info/top_level.txt
FashTextPy-1.1.dist-info/RECORD
