Metadata-Version: 2.1
Name: FashTextPy
Version: 1.1
Summary: Beautiful output to the python console/Красивый вывод в консоль python.
Home-page: https://github.com/Fashons/FashText
Author: Botik1220
Author-email: artemav2006@mail.ru
